MANIFEST.in
README.md
requirements.txt
setup.py
wiki_dump_reader/__init__.py
wiki_dump_reader/cleaner.py
wiki_dump_reader/loader.py
wiki_dump_reader.egg-info/PKG-INFO
wiki_dump_reader.egg-info/SOURCES.txt
wiki_dump_reader.egg-info/dependency_links.txt
wiki_dump_reader.egg-info/top_level.txt