Metadata-Version: 2.1
Name: wiki-dump-reader
Version: 0.0.4
Summary: Extract corpora from Wikipedia dumps
Home-page: https://github.com/CyberZHG/wiki-dump-reader
Author: CyberZHG
Author-email: CyberZHG@gmail.com
License: MIT
Platform: UNKNOWN
Classifier: Programming Language :: Python :: 3
Classifier: License :: OSI Approved :: MIT License
Classifier: Operating System :: OS Independent
